csvtoparquet/__init__.py
csvtoparquet/main.py
csvtoparquet15-0.0.2.dist-info/METADATA
csvtoparquet15-0.0.2.dist-info/WHEEL
csvtoparquet15-0.0.2.dist-info/entry_points.txt
csvtoparquet15-0.0.2.dist-info/top_level.txt
csvtoparquet15-0.0.2.dist-info/RECORD
