Metadata-Version: 2.1
Name: csvtoparquet15
Version: 0.0.2
Summary: A command line tool to convert csv to parquet
Author-email: Zaid Waqi <zaidwaqi@gmail.com>
License: MIT
Project-URL: Homepage, https://github.com/zaidwaqi/csvtoparquet
Project-URL: Issues, https://github.com/pypa/zaidwaqi/csvtoparquet/issues
Classifier: Programming Language :: Python :: 3
Classifier: License :: OSI Approved :: MIT License
Classifier: Operating System :: OS Independent
Requires-Python: >=3.11
Requires-Dist: pyarrow >=14.0.0
